trickkiste/__init__.py
trickkiste/base_tui_app.css
trickkiste/base_tui_app.py
trickkiste/logging_helper.py
trickkiste/misc.py
trickkiste/py.typed
trickkiste/std_suppress.py
trickkiste/examples/decorated.py
trickkiste/examples/fancylogging.py
trickkiste/examples/fancytui.py
trickkiste-0.3.5.dist-info/METADATA
trickkiste-0.3.5.dist-info/WHEEL
trickkiste-0.3.5.dist-info/entry_points.txt
trickkiste-0.3.5.dist-info/RECORD
