Metadata-Version: 2.4
Name: trickkiste
Version: 0.3.5
Summary: Random useful stuff
Project-URL: Repository, https://github.com/frans-fuerst/trickkiste
Author-email: Frans Fürst <frans.fuerst+om-office@protonmail.com>
Requires-Python: <4,>=3.10.4
Requires-Dist: python-dateutil>=2.9.0.post0
